colectica_api/__init__.py
colectica_api/api.py
colectica_api/colectica.py
colectica_api/test_items.py
colectica_api-0.0.10.dist-info/licenses/LICENSE
colectica_api-0.0.10.dist-info/METADATA
colectica_api-0.0.10.dist-info/WHEEL
colectica_api-0.0.10.dist-info/top_level.txt
colectica_api-0.0.10.dist-info/RECORD
