Metadata-Version: 2.4
Name: Colectica_API
Version: 0.0.10
Summary: Python interface to the Colectica API
Author-email: Jenny Li <jenny.li@ucl.ac.uk>
Project-URL: Homepage, https://github.com/CLOSER-Cohorts/colectica_api
Project-URL: Bug Tracker, https://github.com/CLOSER-Cohorts/colectica_api/issues
Classifier: Programming Language :: Python :: 3
Classifier: License :: OSI Approved :: MIT License
Classifier: Operating System :: OS Independent
Requires-Python: >=3.7
License-File: LICENSE
Requires-Dist: pandas>=1.5.3
Requires-Dist: requests
Dynamic: license-file
